{
  "parent": "lifesteal:recipes/root",
  "criteria": {
    "has_heart_core": {
      "conditions": {
        "items": [
          {
            "items": [
              "lifesteal:heart_core"
            ]
          }
        ]
      },
      "trigger": "minecraft:inventory_changed"
    },
    "has_diamond": {
      "conditions": {
        "items": [
          {
            "items": [
              "minecraft:diamond"
            ]
          }
        ]
      },
      "trigger": "minecraft:inventory_changed"
    },
    "has_the_recipe": {
      "conditions": {
        "recipe": "lifesteal:heart_core_block"
      },
      "trigger": "minecraft:recipe_unlocked"
    }
  },
  "requirements": [
    [
      "has_heart_core",
      "has_diamond",
      "has_the_recipe"
    ]
  ],
  "rewards": {
    "recipes": [
      "lifesteal:heart_core_block"
    ]
  }
}